{
  "mode": "pre",
  "tag": "beta",
  "initialVersions": {
    "@directus/api": "13.0.0",
    "@directus/app": "10.7.1",
    "directus": "10.6.1",
    "docs": "0.0.0",
    "@directus/components": "0.0.1",
    "@directus/composables": "10.1.1",
    "@directus/constants": "10.2.3",
    "create-directus-extension": "10.0.10",
    "@directus/data": "0.2.1",
    "@directus/data-driver-postgres": "0.2.1",
    "@directus/data-sql": "0.2.1",
    "@directus/errors": "0.0.2",
    "@directus/extensions-sdk": "10.1.9",
    "@directus/pressure": "1.0.8",
    "@directus/random": "0.2.2",
    "@directus/release-notes-generator": "0.2.0",
    "@directus/schema": "10.0.2",
    "@directus/specs": "10.2.0",
    "@directus/storage": "10.0.5",
    "@directus/storage-driver-azure": "10.0.9",
    "@directus/storage-driver-cloudinary": "10.0.9",
    "@directus/storage-driver-gcs": "10.0.9",
    "@directus/storage-driver-local": "10.0.9",
    "@directus/storage-driver-s3": "10.0.9",
    "@directus/storage-driver-supabase": "1.0.1",
    "@directus/stores": "0.1.2",
    "@directus/themes": "0.0.2",
    "@directus/tsconfig": "1.0.0",
    "@directus/types": "10.1.5",
    "@directus/update-check": "11.0.2",
    "@directus/utils": "10.0.9",
    "@directus/validation": "0.0.4",
    "@directus/sdk": "11.0.3",
    "tests-blackbox": "0.0.0"
  },
  "changesets": []
}
